<?xml version="1.0" encoding="UTF-8" standalone="no"?>
<?xml-stylesheet type="text/xsl" href="calendar.xsl"?>
<temporada xsi:noNamespaceSchemaLocation="calendar.xsd" xmlns:xsi="http://www.w3.org/2001/XMLSchema-instance">
<temporada><numtemp>2021-2022</numtemp><jornada><numero>1</numero><partido><fecha>06/10/2024-08/10/2024</fecha><equipos><local>BNG</local><puntoslocal>0</puntoslocal><visitante>STL</visitante><puntosvisitante>0</puntosvisitante></equipos></partido><partido><fecha>06/10/2024-08/10/2024</fecha><equipos><local>BRS</local><puntoslocal>0</puntoslocal><visitante>CAR</visitante><puntosvisitante>0</puntosvisitante></equipos></partido><partido><fecha>06/10/2024-08/10/2024</fecha><equipos><local>COW</local><puntoslocal>0</puntoslocal><visitante>RDS</visitante><puntosvisitante>0</puntosvisitante></equipos></partido></jornada><jornada><numero>2</numero><partido><fecha>06/10/2024-08/10/2024</fecha><equipos><local>BNG</local><puntoslocal>0</puntoslocal><visitante>STL</visitante><puntosvisitante>0</puntosvisitante></equipos></partido><partido><fecha>06/10/2024-08/10/2024</fecha><equipos><local>BRS</local><puntoslocal>0</puntoslocal><visitante>CAR</visitante><puntosvisitante>0</puntosvisitante></equipos></partido><partido><fecha>06/10/2024-08/10/2024</fecha><equipos><local>COW</local><puntoslocal>0</puntoslocal><visitante>RDS</visitante><puntosvisitante>0</puntosvisitante></equipos></partido></jornada><jornada><numero>3</numero><partido><fecha>06/10/2024-08/10/2024</fecha><equipos><local>BNG</local><puntoslocal>0</puntoslocal><visitante>STL</visitante><puntosvisitante>0</puntosvisitante></equipos></partido><partido><fecha>06/10/2024-08/10/2024</fecha><equipos><local>BRS</local><puntoslocal>0</puntoslocal><visitante>CAR</visitante><puntosvisitante>0</puntosvisitante></equipos></partido><partido><fecha>06/10/2024-08/10/2024</fecha><equipos><local>COW</local><puntoslocal>0</puntoslocal><visitante>RDS</visitante><puntosvisitante>0</puntosvisitante></equipos></partido></jornada><jornada><numero>4</numero><partido><fecha>06/10/2024-08/10/2024</fecha><equipos><local>BNG</local><puntoslocal>0</puntoslocal><visitante>STL</visitante><puntosvisitante>0</puntosvisitante></equipos></partido><partido><fecha>06/10/2024-08/10/2024</fecha><equipos><local>BRS</local><puntoslocal>0</puntoslocal><visitante>CAR</visitante><puntosvisitante>0</puntosvisitante></equipos></partido><partido><fecha>06/10/2024-08/10/2024</fecha><equipos><local>COW</local><puntoslocal>0</puntoslocal><visitante>RDS</visitante><puntosvisitante>0</puntosvisitante></equipos></partido></jornada><jornada><numero>5</numero><partido><fecha>06/10/2024-08/10/2024</fecha><equipos><local>BNG</local><puntoslocal>0</puntoslocal><visitante>STL</visitante><puntosvisitante>0</puntosvisitante></equipos></partido><partido><fecha>06/10/2024-08/10/2024</fecha><equipos><local>BRS</local><puntoslocal>0</puntoslocal><visitante>CAR</visitante><puntosvisitante>0</puntosvisitante></equipos></partido><partido><fecha>06/10/2024-08/10/2024</fecha><equipos><local>COW</local><puntoslocal>0</puntoslocal><visitante>RDS</visitante><puntosvisitante>0</puntosvisitante></equipos></partido></jornada><jornada><numero>6</numero><partido><fecha>06/10/2024-08/10/2024</fecha><equipos><local>BNG</local><puntoslocal>0</puntoslocal><visitante>STL</visitante><puntosvisitante>0</puntosvisitante></equipos></partido><partido><fecha>06/10/2024-08/10/2024</fecha><equipos><local>BRS</local><puntoslocal>0</puntoslocal><visitante>CAR</visitante><puntosvisitante>0</puntosvisitante></equipos></partido><partido><fecha>06/10/2024-08/10/2024</fecha><equipos><local>COW</local><puntoslocal>0</puntoslocal><visitante>RDS</visitante><puntosvisitante>0</puntosvisitante></equipos></partido></jornada><jornada><numero>7</numero><partido><fecha>06/10/2024-08/10/2024</fecha><equipos><local>BNG</local><puntoslocal>0</puntoslocal><visitante>STL</visitante><puntosvisitante>0</puntosvisitante></equipos></partido><partido><fecha>06/10/2024-08/10/2024</fecha><equipos><local>BRS</local><puntoslocal>0</puntoslocal><visitante>CAR</visitante><puntosvisitante>0</puntosvisitante></equipos></partido><partido><fecha>06/10/2024-08/10/2024</fecha><equipos><local>COW</local><puntoslocal>0</puntoslocal><visitante>RDS</visitante><puntosvisitante>0</puntosvisitante></equipos></partido></jornada><jornada><numero>8</numero><partido><fecha>06/10/2024-08/10/2024</fecha><equipos><local>BNG</local><puntoslocal>0</puntoslocal><visitante>STL</visitante><puntosvisitante>0</puntosvisitante></equipos></partido><partido><fecha>06/10/2024-08/10/2024</fecha><equipos><local>BRS</local><puntoslocal>0</puntoslocal><visitante>CAR</visitante><puntosvisitante>0</puntosvisitante></equipos></partido><partido><fecha>06/10/2024-08/10/2024</fecha><equipos><local>COW</local><puntoslocal>0</puntoslocal><visitante>RDS</visitante><puntosvisitante>0</puntosvisitante></equipos></partido></jornada><jornada><numero>9</numero><partido><fecha>06/10/2024-08/10/2024</fecha><equipos><local>BNG</local><puntoslocal>0</puntoslocal><visitante>STL</visitante><puntosvisitante>0</puntosvisitante></equipos></partido><partido><fecha>06/10/2024-08/10/2024</fecha><equipos><local>BRS</local><puntoslocal>0</puntoslocal><visitante>CAR</visitante><puntosvisitante>0</puntosvisitante></equipos></partido><partido><fecha>06/10/2024-08/10/2024</fecha><equipos><local>COW</local><puntoslocal>0</puntoslocal><visitante>RDS</visitante><puntosvisitante>0</puntosvisitante></equipos></partido></jornada><jornada><numero>10</numero><partido><fecha>06/10/2024-08/10/2024</fecha><equipos><local>BNG</local><puntoslocal>0</puntoslocal><visitante>STL</visitante><puntosvisitante>0</puntosvisitante></equipos></partido><partido><fecha>06/10/2024-08/10/2024</fecha><equipos><local>BRS</local><puntoslocal>0</puntoslocal><visitante>CAR</visitante><puntosvisitante>0</puntosvisitante></equipos></partido><partido><fecha>06/10/2024-08/10/2024</fecha><equipos><local>COW</local><puntoslocal>0</puntoslocal><visitante>RDS</visitante><puntosvisitante>0</puntosvisitante></equipos></partido></jornada></temporada>